tfr/__init__.py
tfr/plots.py
tfr/reassignment.py
tfr/signal.py
tfr/sklearn.py
tfr/spectrogram.py
tfr/spectrogram_features.py
tfr/tuning.py
tfr-0.2.4.dist-info/METADATA
tfr-0.2.4.dist-info/RECORD
tfr-0.2.4.dist-info/WHEEL
tfr-0.2.4.dist-info/entry_points.txt
tfr-0.2.4.dist-info/top_level.txt
